{"status": "Success", "rating": 2894, "stars": "7\u2605", "highest_rating": 2978, "global_rank": 11, "country_rank": 4, "user_details": {"name": "BaekI Hwang", "username": "kut_hbi1998", "country": "North Korea", "state": "Pyongyang", "city": "Pyongyang", "student/professional": "Student", "institution": "Kim Chaek University of Technology"}, "contests": [{"name": "Long Challenge", "rating": 2902, "global_rank": 5, "country_rank": 4}, {"name": "Cook-off", "rating": 1700, "global_rank": 5720, "country_rank": 10}, {"name": "Lunch Time", "rating": 0, "global_rank": "NA", "country_rank": "NA"}], "contest_ratings": [{"code": "COOK82", "getyear": "2017", "getmonth": "5", "getday": "22", "reason": null, "penalised_in": null, "rating": "1775", "rank": "12", "name": "May Cook-Off 2017", "end_date": "2017-05-22 00:00:00"}, {"code": "AUG17", "getyear": "2017", "getmonth": "8", "getday": "18", "reason": null, "penalised_in": null, "rating": "1771", "rank": "2060", "name": "August Long Challenge 2017", "end_date": "2017-08-18 15:00:00"}, {"code": "DEC17", "getyear": "2017", "getmonth": "12", "getday": "11", "reason": null, "penalised_in": null, "rating": "1961", "rank": "5", "name": "December Challenge 2017", "end_date": "2017-12-11 15:00:00"}, {"code": "JAN18", "getyear": "2018", "getmonth": "1", "getday": "15", "reason": null, "penalised_in": null, "rating": "1956", "rank": "1186", "name": "January Challenge 2018", "end_date": "2018-01-15 15:00:00"}, {"code": "FEB18", "getyear": "2018", "getmonth": "2", "getday": "12", "reason": null, "penalised_in": null, "rating": "2124", "rank": "4", "name": "February Challenge 2018", "end_date": "2018-02-12 15:00:00"}, {"code": "OCT18A", "getyear": "2018", "getmonth": "10", "getday": "20", "reason": null, "penalised_in": null, "rating": "2281", "rank": "1", "name": "October Challenge 2018 Division 1", "end_date": "2018-10-20 15:00:00"}, {"code": "NOV18A", "getyear": "2018", "getmonth": "11", "getday": "12", "reason": null, "penalised_in": null, "rating": "2431", "rank": "2", "name": "November Challenge 2018 Division 1", "end_date": "2018-11-12 15:00:00"}, {"code": "DEC18A", "getyear": "2018", "getmonth": "12", "getday": "18", "reason": null, "penalised_in": null, "rating": "2572", "rank": "6", "name": "December Challenge 2018 Division 1", "end_date": "2018-12-18 01:00:00"}, {"code": "JAN19A", "getyear": "2019", "getmonth": "1", "getday": "14", "reason": null, "penalised_in": null, "rating": "2688", "rank": "5", "name": "January Challenge 2019 Division 1", "end_date": "2019-01-14 15:00:00"}, {"code": "FEB19A", "getyear": "2019", "getmonth": "2", "getday": "13", "reason": null, "penalised_in": null, "rating": "2826", "rank": "2", "name": "February Challenge 2019 Division 1", "end_date": "2019-02-13 15:00:00"}, {"code": "MARCH19A", "getyear": "2019", "getmonth": "3", "getday": "13", "reason": null, "penalised_in": null, "rating": "2910", "rank": "2", "name": "March Challenge 2019 Division 1", "end_date": "2019-03-13 15:00:00"}, {"code": "APRIL19A", "getyear": "2019", "getmonth": "4", "getday": "15", "reason": null, "penalised_in": null, "rating": "2978", "rank": "1", "name": "April Challenge 2019 Division 1", "end_date": "2019-04-15 15:00:00"}, {"code": "COME2019", "getyear": "2019", "getmonth": "4", "getday": "17", "reason": null, "penalised_in": null, "rating": "2886", "rank": "3", "name": "Code Melange (Rated for all)", "end_date": "2019-04-17 00:00:00"}, {"code": "MAY19A", "getyear": "2019", "getmonth": "5", "getday": "13", "reason": null, "penalised_in": null, "rating": "2956", "rank": "1", "name": "May Challenge 2019 Division 1", "end_date": "2019-05-13 15:00:00"}, {"code": "SEPT20A", "getyear": "2020", "getmonth": "9", "getday": "14", "reason": null, "penalised_in": null, "rating": "2894", "rank": "3", "name": "September Challenge 2020 Division 1", "end_date": "2020-09-14 15:00:00"}], "fully_solved": {"count": 130, "Practice": [{"name": "BIAS", "link": "https://www.codechef.com/status/BIAS,kut_hbi1998"}, {"name": "TMP01", "link": "https://www.codechef.com/status/TMP01,kut_hbi1998"}, {"name": "GCDTREE", "link": "https://www.codechef.com/status/GCDTREE,kut_hbi1998"}, {"name": "DIFTRIP", "link": "https://www.codechef.com/status/DIFTRIP,kut_hbi1998"}, {"name": "TUPLES2", "link": "https://www.codechef.com/status/TUPLES2,kut_hbi1998"}, {"name": "CHEFC", "link": "https://www.codechef.com/status/CHEFC,kut_hbi1998"}, {"name": "CHORCKIT", "link": "https://www.codechef.com/status/CHORCKIT,kut_hbi1998"}, {"name": "VBR", "link": "https://www.codechef.com/status/VBR,kut_hbi1998"}], "COOK82": [{"name": "COOK82A", "link": "https://www.codechef.com/COOK82/status/COOK82A,kut_hbi1998"}, {"name": "COOK82B", "link": "https://www.codechef.com/COOK82/status/COOK82B,kut_hbi1998"}, {"name": "COOK82D", "link": "https://www.codechef.com/COOK82/status/COOK82D,kut_hbi1998"}, {"name": "COOK82C", "link": "https://www.codechef.com/COOK82/status/COOK82C,kut_hbi1998"}], "COOK84": [{"name": "CHNGFUNC", "link": "https://www.codechef.com/COOK84/status/CHNGFUNC,kut_hbi1998"}, {"name": "CHNGOR", "link": "https://www.codechef.com/COOK84/status/CHNGOR,kut_hbi1998"}, {"name": "CHNGSUM", "link": "https://www.codechef.com/COOK84/status/CHNGSUM,kut_hbi1998"}, {"name": "BIPARTRE", "link": "https://www.codechef.com/COOK84/status/BIPARTRE,kut_hbi1998"}], "AUG17": [{"name": "CHEFMOVR", "link": "https://www.codechef.com/AUG17/status/CHEFMOVR,kut_hbi1998"}, {"name": "RAINBOWA", "link": "https://www.codechef.com/AUG17/status/RAINBOWA,kut_hbi1998"}, {"name": "GCAC", "link": "https://www.codechef.com/AUG17/status/GCAC,kut_hbi1998"}, {"name": "PALINGAM", "link": "https://www.codechef.com/AUG17/status/PALINGAM,kut_hbi1998"}], "DEC17": [{"name": "GIT01", "link": "https://www.codechef.com/DEC17/status/GIT01,kut_hbi1998"}, {"name": "CPLAY", "link": "https://www.codechef.com/DEC17/status/CPLAY,kut_hbi1998"}, {"name": "VK18", "link": "https://www.codechef.com/DEC17/status/VK18,kut_hbi1998"}, {"name": "CHEFHAM", "link": "https://www.codechef.com/DEC17/status/CHEFHAM,kut_hbi1998"}, {"name": "CHEFUNI", "link": "https://www.codechef.com/DEC17/status/CHEFUNI,kut_hbi1998"}, {"name": "REDBLUE", "link": "https://www.codechef.com/DEC17/status/REDBLUE,kut_hbi1998"}, {"name": "CHEFEXQ", "link": "https://www.codechef.com/DEC17/status/CHEFEXQ,kut_hbi1998"}, {"name": "WESTAND", "link": "https://www.codechef.com/DEC17/status/WESTAND,kut_hbi1998"}, {"name": "CHEFFIB", "link": "https://www.codechef.com/DEC17/status/CHEFFIB,kut_hbi1998"}, {"name": "DSANTAP", "link": "https://www.codechef.com/DEC17/status/DSANTAP,kut_hbi1998"}], "JAN18": [{"name": "RECTANGL", "link": "https://www.codechef.com/JAN18/status/RECTANGL,kut_hbi1998"}, {"name": "STRMRG", "link": "https://www.codechef.com/JAN18/status/STRMRG,kut_hbi1998"}, {"name": "CHEFPALS", "link": "https://www.codechef.com/JAN18/status/CHEFPALS,kut_hbi1998"}, {"name": "KCON", "link": "https://www.codechef.com/JAN18/status/KCON,kut_hbi1998"}, {"name": "MAXSC", "link": "https://www.codechef.com/JAN18/status/MAXSC,kut_hbi1998"}, {"name": "PRTITION", "link": "https://www.codechef.com/JAN18/status/PRTITION,kut_hbi1998"}], "FEB18": [{"name": "CHEFCHR", "link": "https://www.codechef.com/FEB18/status/CHEFCHR,kut_hbi1998"}, {"name": "CHEFPTNT", "link": "https://www.codechef.com/FEB18/status/CHEFPTNT,kut_hbi1998"}, {"name": "CARPTUN", "link": "https://www.codechef.com/FEB18/status/CARPTUN,kut_hbi1998"}, {"name": "BROCLK", "link": "https://www.codechef.com/FEB18/status/BROCLK,kut_hbi1998"}, {"name": "POINPOLY", "link": "https://www.codechef.com/FEB18/status/POINPOLY,kut_hbi1998"}, {"name": "PERMPAL", "link": "https://www.codechef.com/FEB18/status/PERMPAL,kut_hbi1998"}, {"name": "CLANDLBL", "link": "https://www.codechef.com/FEB18/status/CLANDLBL,kut_hbi1998"}, {"name": "BIAS", "link": "https://www.codechef.com/FEB18/status/BIAS,kut_hbi1998"}, {"name": "CHANOQ", "link": "https://www.codechef.com/FEB18/status/CHANOQ,kut_hbi1998"}, {"name": "LUCASTH", "link": "https://www.codechef.com/FEB18/status/LUCASTH,kut_hbi1998"}], "CODH2018": [{"name": "THC1", "link": "https://www.codechef.com/CODH2018/status/THC1,kut_hbi1998"}], "OCT18A": [{"name": "BBRICKS", "link": "https://www.codechef.com/OCT18A/status/BBRICKS,kut_hbi1998"}, {"name": "HMAPPY", "link": "https://www.codechef.com/OCT18A/status/HMAPPY,kut_hbi1998"}, {"name": "MINDSUM", "link": "https://www.codechef.com/OCT18A/status/MINDSUM,kut_hbi1998"}, {"name": "SURCHESS", "link": "https://www.codechef.com/OCT18A/status/SURCHESS,kut_hbi1998"}, {"name": "TREEWALK", "link": "https://www.codechef.com/OCT18A/status/TREEWALK,kut_hbi1998"}, {"name": "DISTRING", "link": "https://www.codechef.com/OCT18A/status/DISTRING,kut_hbi1998"}, {"name": "CPCOMP", "link": "https://www.codechef.com/OCT18A/status/CPCOMP,kut_hbi1998"}], "NOV18A": [{"name": "GMEDIAN", "link": "https://www.codechef.com/NOV18A/status/GMEDIAN,kut_hbi1998"}, {"name": "HMAPPY1", "link": "https://www.codechef.com/NOV18A/status/HMAPPY1,kut_hbi1998"}, {"name": "MAGICHF2", "link": "https://www.codechef.com/NOV18A/status/MAGICHF2,kut_hbi1998"}, {"name": "CHEFEQUA", "link": "https://www.codechef.com/NOV18A/status/CHEFEQUA,kut_hbi1998"}, {"name": "RECIPES", "link": "https://www.codechef.com/NOV18A/status/RECIPES,kut_hbi1998"}, {"name": "BINSTR", "link": "https://www.codechef.com/NOV18A/status/BINSTR,kut_hbi1998"}, {"name": "MAXDTREE", "link": "https://www.codechef.com/NOV18A/status/MAXDTREE,kut_hbi1998"}, {"name": "PRITREE", "link": "https://www.codechef.com/NOV18A/status/PRITREE,kut_hbi1998"}], "DEC18A": [{"name": "MAXEP", "link": "https://www.codechef.com/DEC18A/status/MAXEP,kut_hbi1998"}, {"name": "INTXOR", "link": "https://www.codechef.com/DEC18A/status/INTXOR,kut_hbi1998"}, {"name": "EDGEDIR", "link": "https://www.codechef.com/DEC18A/status/EDGEDIR,kut_hbi1998"}, {"name": "BICONT", "link": "https://www.codechef.com/DEC18A/status/BICONT,kut_hbi1998"}, {"name": "CBFEAST", "link": "https://www.codechef.com/DEC18A/status/CBFEAST,kut_hbi1998"}, {"name": "BHD", "link": "https://www.codechef.com/DEC18A/status/BHD,kut_hbi1998"}, {"name": "DLDAG", "link": "https://www.codechef.com/DEC18A/status/DLDAG,kut_hbi1998"}], "JAN19A": [{"name": "GRAPART", "link": "https://www.codechef.com/JAN19A/status/GRAPART,kut_hbi1998"}, {"name": "XYPIZQ", "link": "https://www.codechef.com/JAN19A/status/XYPIZQ,kut_hbi1998"}, {"name": "DPAIRS", "link": "https://www.codechef.com/JAN19A/status/DPAIRS,kut_hbi1998"}, {"name": "EARTSEQ", "link": "https://www.codechef.com/JAN19A/status/EARTSEQ,kut_hbi1998"}, {"name": "DIFNEIGH", "link": "https://www.codechef.com/JAN19A/status/DIFNEIGH,kut_hbi1998"}, {"name": "PARRTY", "link": "https://www.codechef.com/JAN19A/status/PARRTY,kut_hbi1998"}, {"name": "MXDIST", "link": "https://www.codechef.com/JAN19A/status/MXDIST,kut_hbi1998"}, {"name": "MATCHIT", "link": "https://www.codechef.com/JAN19A/status/MATCHIT,kut_hbi1998"}], "FEB19A": [{"name": "MANRECT", "link": "https://www.codechef.com/FEB19A/status/MANRECT,kut_hbi1998"}, {"name": "GUESSRT", "link": "https://www.codechef.com/FEB19A/status/GUESSRT,kut_hbi1998"}, {"name": "ARTBALAN", "link": "https://www.codechef.com/FEB19A/status/ARTBALAN,kut_hbi1998"}, {"name": "CHEFING", "link": "https://www.codechef.com/FEB19A/status/CHEFING,kut_hbi1998"}, {"name": "XDCOMP", "link": "https://www.codechef.com/FEB19A/status/XDCOMP,kut_hbi1998"}, {"name": "TRDST", "link": "https://www.codechef.com/FEB19A/status/TRDST,kut_hbi1998"}, {"name": "MAXTAX", "link": "https://www.codechef.com/FEB19A/status/MAXTAX,kut_hbi1998"}, {"name": "CHORCKIT", "link": "https://www.codechef.com/FEB19A/status/CHORCKIT,kut_hbi1998"}], "MARCH19A": [{"name": "SUBPRNJL", "link": "https://www.codechef.com/MARCH19A/status/SUBPRNJL,kut_hbi1998"}, {"name": "TREASURE", "link": "https://www.codechef.com/MARCH19A/status/TREASURE,kut_hbi1998"}, {"name": "CHONQ", "link": "https://www.codechef.com/MARCH19A/status/CHONQ,kut_hbi1998"}, {"name": "CHEFSOC", "link": "https://www.codechef.com/MARCH19A/status/CHEFSOC,kut_hbi1998"}, {"name": "MATPER", "link": "https://www.codechef.com/MARCH19A/status/MATPER,kut_hbi1998"}, {"name": "PTREE", "link": "https://www.codechef.com/MARCH19A/status/PTREE,kut_hbi1998"}, {"name": "SONATR", "link": "https://www.codechef.com/MARCH19A/status/SONATR,kut_hbi1998"}, {"name": "INTERLEA", "link": "https://www.codechef.com/MARCH19A/status/INTERLEA,kut_hbi1998"}], "APRIL19A": [{"name": "SUBREM", "link": "https://www.codechef.com/APRIL19A/status/SUBREM,kut_hbi1998"}, {"name": "SJ1", "link": "https://www.codechef.com/APRIL19A/status/SJ1,kut_hbi1998"}, {"name": "CHEFOFR", "link": "https://www.codechef.com/APRIL19A/status/CHEFOFR,kut_hbi1998"}, {"name": "KLPM", "link": "https://www.codechef.com/APRIL19A/status/KLPM,kut_hbi1998"}, {"name": "XORMIN", "link": "https://www.codechef.com/APRIL19A/status/XORMIN,kut_hbi1998"}, {"name": "EDGY", "link": "https://www.codechef.com/APRIL19A/status/EDGY,kut_hbi1998"}, {"name": "SONIQUE", "link": "https://www.codechef.com/APRIL19A/status/SONIQUE,kut_hbi1998"}, {"name": "RECTARAN", "link": "https://www.codechef.com/APRIL19A/status/RECTARAN,kut_hbi1998"}], "COME2019": [{"name": "MAX2", "link": "https://www.codechef.com/COME2019/status/MAX2,kut_hbi1998"}, {"name": "SMALLARR", "link": "https://www.codechef.com/COME2019/status/SMALLARR,kut_hbi1998"}, {"name": "GREG", "link": "https://www.codechef.com/COME2019/status/GREG,kut_hbi1998"}, {"name": "XOMMON", "link": "https://www.codechef.com/COME2019/status/XOMMON,kut_hbi1998"}, {"name": "RNDRND", "link": "https://www.codechef.com/COME2019/status/RNDRND,kut_hbi1998"}, {"name": "SUBNUM", "link": "https://www.codechef.com/COME2019/status/SUBNUM,kut_hbi1998"}, {"name": "SWAPSIGN", "link": "https://www.codechef.com/COME2019/status/SWAPSIGN,kut_hbi1998"}, {"name": "OPTSPL", "link": "https://www.codechef.com/COME2019/status/OPTSPL,kut_hbi1998"}, {"name": "IMPACT", "link": "https://www.codechef.com/COME2019/status/IMPACT,kut_hbi1998"}], "MAY19A": [{"name": "SONGIF", "link": "https://www.codechef.com/MAY19A/status/SONGIF,kut_hbi1998"}, {"name": "CUREK", "link": "https://www.codechef.com/MAY19A/status/CUREK,kut_hbi1998"}, {"name": "WTBTR", "link": "https://www.codechef.com/MAY19A/status/WTBTR,kut_hbi1998"}, {"name": "ADAROKS2", "link": "https://www.codechef.com/MAY19A/status/ADAROKS2,kut_hbi1998"}, {"name": "TREDEG", "link": "https://www.codechef.com/MAY19A/status/TREDEG,kut_hbi1998"}, {"name": "PKLVES", "link": "https://www.codechef.com/MAY19A/status/PKLVES,kut_hbi1998"}, {"name": "ADAPWN", "link": "https://www.codechef.com/MAY19A/status/ADAPWN,kut_hbi1998"}, {"name": "CHEFXCHG", "link": "https://www.codechef.com/MAY19A/status/CHEFXCHG,kut_hbi1998"}], "NACA2019": [{"name": "STGAME", "link": "https://www.codechef.com/NACA2019/status/STGAME,kut_hbi1998"}, {"name": "HELL", "link": "https://www.codechef.com/NACA2019/status/HELL,kut_hbi1998"}, {"name": "FNEE", "link": "https://www.codechef.com/NACA2019/status/FNEE,kut_hbi1998"}, {"name": "NUMTED", "link": "https://www.codechef.com/NACA2019/status/NUMTED,kut_hbi1998"}], "SEPT20A": [{"name": "EQDIV", "link": "https://www.codechef.com/SEPT20A/status/EQDIV,kut_hbi1998"}, {"name": "ADAMAT", "link": "https://www.codechef.com/SEPT20A/status/ADAMAT,kut_hbi1998"}, {"name": "MOVCOIN2", "link": "https://www.codechef.com/SEPT20A/status/MOVCOIN2,kut_hbi1998"}, {"name": "CHFNSWAP", "link": "https://www.codechef.com/SEPT20A/status/CHFNSWAP,kut_hbi1998"}, {"name": "FINXOR", "link": "https://www.codechef.com/SEPT20A/status/FINXOR,kut_hbi1998"}, {"name": "CRDGAME2", "link": "https://www.codechef.com/SEPT20A/status/CRDGAME2,kut_hbi1998"}, {"name": "MVCN2TST", "link": "https://www.codechef.com/SEPT20A/status/MVCN2TST,kut_hbi1998"}, {"name": "CHEFSUMS", "link": "https://www.codechef.com/SEPT20A/status/CHEFSUMS,kut_hbi1998"}, {"name": "ROTATPOL", "link": "https://www.codechef.com/SEPT20A/status/ROTATPOL,kut_hbi1998"}, {"name": "VBR", "link": "https://www.codechef.com/SEPT20A/status/VBR,kut_hbi1998"}]}, "partially_solved": {"count": 2, "JAN18": [{"name": "MONSTER", "link": "https://www.codechef.com/JAN18/status/MONSTER,kut_hbi1998"}], "DEC18A": [{"name": "WKPLAN", "link": "https://www.codechef.com/DEC18A/status/WKPLAN,kut_hbi1998"}]}}